hmcc_sorting/__init__.py
hmcc_sorting/bubble_sort.py
hmcc_sorting/insertion_sort.py
hmcc_sorting/quick_sort.py
hmcc_sorting/selection_sort.py
hmcc_sorting-0.1.dist-info/METADATA
hmcc_sorting-0.1.dist-info/WHEEL
hmcc_sorting-0.1.dist-info/top_level.txt
hmcc_sorting-0.1.dist-info/RECORD
