Metadata-Version: 2.1
Name: hmcc-sorting
Version: 0.1
Summary: Package to sort lists
Home-page: UNKNOWN
Author: hmcc
Author-email: something@example.com
License: MIT
Platform: UNKNOWN
